mcresources/__init__.py
mcresources/advancements.py
mcresources/atlases.py
mcresources/block_context.py
mcresources/block_states.py
mcresources/item_context.py
mcresources/loot_tables.py
mcresources/py.typed
mcresources/recipe_context.py
mcresources/resource_manager.py
mcresources/surface_rules.py
mcresources/tag.py
mcresources/type_definitions.py
mcresources/utils.py
mcresources-1.7.5.dist-info/licenses/LICENSE.txt
mcresources-1.7.5.dist-info/METADATA
mcresources-1.7.5.dist-info/WHEEL
mcresources-1.7.5.dist-info/top_level.txt
mcresources-1.7.5.dist-info/RECORD
