Metadata-Version: 2.4
Name: mcresources
Version: 1.7.5
Summary: A Python Data Generator for Minecraft Modding
Home-page: https://github.com/TerraFirmaCraft/mcresources
Author: EERussianguy
Author-email: eerussianguy@gmail.com
License: MIT
Keywords: python,minecraft,resources,modding,forge,neoforge
Classifier: Development Status :: 5 - Production/Stable
Classifier: Intended Audience :: Developers
Classifier: License :: OSI Approved :: MIT License
Classifier: Programming Language :: Python :: 3.7
License-File: LICENSE.txt
Dynamic: author
Dynamic: author-email
Dynamic: classifier
Dynamic: description
Dynamic: description-content-type
Dynamic: home-page
Dynamic: keywords
Dynamic: license
Dynamic: license-file
Dynamic: summary
